{
  "databaseName": "phase20-19-local-only-safety-continuity-panel-summary-db",
  "phase": "Phase20-19",
  "panelStatus": "local_only_safety_continuity_plan_only",
  "phase20_19_summary": {
    "totalSafetyChecks": 10,
    "repositoryPrivatePremise": true,
    "localLaunchPolicy": "start-local.bat / private-local.html / index.html only",
    "startLocalBatRouteAllowed": true,
    "privateLocalHtmlRouteAllowed": true,
    "indexHtmlRouteAllowed": true,
    "githubPagesPublicUrlLaunchAllowed": false,
    "publicUrlLaunchAllowed": false,
    "localLaunchOnly": true,
    "phase20_12_to_18_locks_preserved": true,
    "localOnlySafeToContinue": true,
    "protectedMode": true,
    "planOnly": true,
    "privateLocalPolicyUnchanged": true,
    "externalConnection": false,
    "externalConnectionAllowed": false,
    "autoPublish": false,
    "autoPublishAllowed": false,
    "autoExecution": false,
    "autoExecutionAllowed": false,
    "autoLaunch": false,
    "autoLaunchAllowed": false,
    "githubPagesChangeAllowed": false,
    "githubPagesSettingChangeAllowed": false,
    "repositoryVisibilityChangeAllowed": false,
    "publicReleaseBlocked": true,
    "publicReleaseAllowed": false,
    "manualConfirmationRequiredBeforePublicRelease": true,
    "manualOwnerConfirmationRequired": true,
    "ownerApprovalLockActive": true,
    "finalPublicReleaseBlock": true,
    "allDeviceConfirmationsApproved": false,
    "publicReleaseReady": false,
    "unsafeFlagsCount": 0,
    "nextRecommendedStep": "Continue private local-only review with Phase20-12 through Phase20-18 locks preserved"
  },
  "allowedActions": ["plan", "review", "validate", "audit", "report", "local_launch", "dashboard_view"],
  "blockedActions": [
    "public_url_exposure",
    "external_connection",
    "auto_publish",
    "auto_execution",
    "auto_launch",
    "github_pages_setting_change",
    "repository_visibility_change",
    "public_release_without_all_device_confirmations",
    "public_release_without_manual_owner_confirmation",
    "owner_release_unlock_without_manual_confirmation",
    "safety_lock_bypass",
    "private_policy_override",
    "dashboard_public_release_enable",
    "non_local_launch"
  ]
}
